git_fortune/__init__.py
git_fortune/_compat.py
git_fortune/cli.py
git_fortune/database.py
git_fortune/formatter.py
git_fortune/version.py
git_fortune-0.0.4.dist-info/COPYING
git_fortune-0.0.4.dist-info/LICENSE
git_fortune-0.0.4.dist-info/METADATA
git_fortune-0.0.4.dist-info/WHEEL
git_fortune-0.0.4.dist-info/entry_points.txt
git_fortune-0.0.4.dist-info/top_level.txt
git_fortune-0.0.4.dist-info/RECORD
