Metadata-Version: 2.1
Name: git-fortune
Version: 0.0.4
Summary: fortune-like git tips
Home-page: https://github.com/sirosen/git-fortune
Author: Stephen Rosen
Author-email: sirosen@uchicago.edu
License: UNKNOWN
Keywords: fortune,git
Platform: UNKNOWN
Classifier: Development Status :: 3 - Alpha
Classifier: Intended Audience :: Developers
Classifier: License :: OSI Approved :: Apache Software License
Classifier: Operating System :: POSIX
Classifier: Programming Language :: Python
Classifier: Programming Language :: Python :: 2.7
Classifier: Programming Language :: Python :: 3.4
Classifier: Programming Language :: Python :: 3.5
Classifier: Programming Language :: Python :: 3.6
Classifier: Programming Language :: Python :: 3.7
Provides-Extra: development
Requires-Dist: pytest (<5,>=4.3.1) ; extra == 'development'
Requires-Dist: pytest-cov (<3,>=2.6.1) ; extra == 'development'
Requires-Dist: flake8 (<4.0,>=3.7.7) ; extra == 'development'
Requires-Dist: isort (<5.0,>=4.3.15) ; extra == 'development'
Requires-Dist: mock (==2.0.0) ; (python_version < "3.6") and extra == 'development'
Requires-Dist: flake8-bugbear (==18.8.0) ; (python_version >= "3.5") and extra == 'development'
Requires-Dist: black (==19.3b) ; (python_version >= "3.6") and extra == 'development'
